LICENSE
MANIFEST.in
README.md
setup.py
shiftpy/__init__.py
shiftpy/env.py
shiftpy/wsgi_utils.py
shiftpy.egg-info/PKG-INFO
shiftpy.egg-info/SOURCES.txt
shiftpy.egg-info/dependency_links.txt
shiftpy.egg-info/not-zip-safe
shiftpy.egg-info/top_level.txt
tests/__init__.py
tests/conftest.py
tests/test_basic.py