Metadata-Version: 1.0
Name: shiftpy
Version: 0.1.3
Summary: Tools for Python Apps on OpenShift Red Hat Cloud
Home-page: https://github.com/rochacbruno/shiftpy/
Author: Bruno Rocha
Author-email: rochacbruno@gmail.com
License: MIT
Platform: any
